coinone/__init__.py
coinone/core.py
coinone/error.py
coinone/raw.py
coinone/api/__init__.py
coinone/api/base.py
coinone/api/common/__init__.py
coinone/api/common/account.py
coinone/api/common/enums.py
coinone/api/common/order.py
coinone/api/common/public.py
coinone/api/common/transaction.py
coinone/api/v1/__init__.py
coinone/api/v1/account.py
coinone/api/v1/order.py
coinone/api/v1/transaction.py
coinone/api/v2/__init__.py
coinone/api/v2/account.py
coinone/api/v2/order.py
coinone/api/v2/transaction.py
pycoinone-2018.4.24.dist-info/METADATA
pycoinone-2018.4.24.dist-info/RECORD
pycoinone-2018.4.24.dist-info/WHEEL
pycoinone-2018.4.24.dist-info/top_level.txt
